kindabool/__init__.py
kindabool/kinda_bool.py
kindabool-1.0.0.dist-info/LICENSE
kindabool-1.0.0.dist-info/METADATA
kindabool-1.0.0.dist-info/WHEEL
kindabool-1.0.0.dist-info/top_level.txt
kindabool-1.0.0.dist-info/RECORD
