Metadata-Version: 2.1
Name: kindabool
Version: 1.0.0
Summary: A python package for things that are only kinda true.
Home-page: https://github.com/kamudi/kindabool
Author: kamudi
License: MIT
Keywords: bool boolean kindabool kinda_bool kinda_boolean
License-File: LICENSE
